[
    {
      "id": "lapua-223rem-55gr-fmj",
      "name": "Lapua .223 Rem 55gr FMJ",
      "type": "centerfire",
      "manufacturerBullet": "Lapua",
      "bulletName": "FMJ",
      "bulletWeight": 55,
      "bulletWeightUnit": "gr",
      "bulletBc": 0.267,
      "bulletBcModel": "g1",
      "caliber": ".223 Rem",
      "caliberId": "223rem",
      "caliberMm": 5.56,
      "manufacturerCase": "Lapua"
    },
    {
      "id": "lapua-223rem-69gr-hpbt-scenar",
      "name": "Lapua .223 Rem 69gr HPBT Scenar",
      "type": "centerfire",
      "manufacturerBullet": "Lapua",
      "bulletName": "Scenar HPBT",
      "bulletWeight": 69,
      "bulletWeightUnit": "gr",
      "bulletBc": 0.315,
      "bulletBcModel": "g1",
      "caliber": ".223 Rem",
      "caliberId": "223rem",
      "caliberMm": 5.56,
      "manufacturerCase": "Lapua"
    },
    {
      "id": "lapua-223rem-77gr-hpbt-scenar",
      "name": "Lapua .223 Rem 77gr HPBT Scenar",
      "type": "centerfire",
      "manufacturerBullet": "Lapua",
      "bulletName": "Scenar HPBT",
      "bulletWeight": 77,
      "bulletWeightUnit": "gr",
      "bulletBc": 0.372,
      "bulletBcModel": "g1",
      "caliber": ".223 Rem",
      "caliberId": "223rem",
      "caliberMm": 5.56,
      "manufacturerCase": "Lapua"
    },
    {
      "id": "lapua-308win-150gr-fmj",
      "name": "Lapua .308 Win 150gr FMJ",
      "type": "centerfire",
      "manufacturerBullet": "Lapua",
      "bulletName": "FMJ",
      "bulletWeight": 150,
      "bulletWeightUnit": "gr",
      "bulletBc": 0.387,
      "bulletBcModel": "g1",
      "caliber": ".308 Win",
      "caliberId": "308win",
      "caliberMm": 7.62,
      "manufacturerCase": "Lapua"
    },
    {
      "id": "lapua-308win-167gr-hpbt-scenar",
      "name": "Lapua .308 Win 167gr HPBT Scenar",
      "type": "centerfire",
      "manufacturerBullet": "Lapua",
      "bulletName": "Scenar HPBT",
      "bulletWeight": 167,
      "bulletWeightUnit": "gr",
      "bulletBc": 0.47,
      "bulletBcModel": "g1",
      "caliber": ".308 Win",
      "caliberId": "308win",
      "caliberMm": 7.62,
      "manufacturerCase": "Lapua"
    },
    {
      "id": "lapua-308win-175gr-hpbt-scenar",
      "name": "Lapua .308 Win 175gr HPBT Scenar",
      "type": "centerfire",
      "manufacturerBullet": "Lapua",
      "bulletName": "Scenar HPBT",
      "bulletWeight": 175,
      "bulletWeightUnit": "gr",
      "bulletBc": 0.505,
      "bulletBcModel": "g1",
      "caliber": ".308 Win",
      "caliberId": "308win",
      "caliberMm": 7.62,
      "manufacturerCase": "Lapua"
    },
    {
      "id": "lapua-308win-185gr-hpbt-scenar",
      "name": "Lapua .308 Win 185gr HPBT Scenar",
      "type": "centerfire",
      "manufacturerBullet": "Lapua",
      "bulletName": "Scenar HPBT",
      "bulletWeight": 185,
      "bulletWeightUnit": "gr",
      "bulletBc": 0.521,
      "bulletBcModel": "g1",
      "caliber": ".308 Win",
      "caliberId": "308win",
      "caliberMm": 7.62,
      "manufacturerCase": "Lapua"
    },
    {
      "id": "lapua-308win-155gr-hpbt-scenar-l",
      "name": "Lapua .308 Win 155gr HPBT Scenar-L",
      "type": "centerfire",
      "manufacturerBullet": "Lapua",
      "bulletName": "Scenar-L HPBT",
      "bulletWeight": 155,
      "bulletWeightUnit": "gr",
      "bulletBc": 0.508,
      "bulletBcModel": "g1",
      "caliber": ".308 Win",
      "caliberId": "308win",
      "caliberMm": 7.62,
      "manufacturerCase": "Lapua"
    },
    {
      "id": "lapua-308win-185gr-hpbt-scenar-l",
      "name": "Lapua .308 Win 185gr HPBT Scenar-L",
      "type": "centerfire",
      "manufacturerBullet": "Lapua",
      "bulletName": "Scenar-L HPBT",
      "bulletWeight": 185,
      "bulletWeightUnit": "gr",
      "bulletBc": 0.535,
      "bulletBcModel": "g1",
      "caliber": ".308 Win",
      "caliberId": "308win",
      "caliberMm": 7.62,
      "manufacturerCase": "Lapua"
    },
    {
      "id": "lapua-308win-200gr-hpbt-scenar",
      "name": "Lapua .308 Win 200gr HPBT Scenar",
      "type": "centerfire",
      "manufacturerBullet": "Lapua",
      "bulletName": "Scenar HPBT",
      "bulletWeight": 200,
      "bulletWeightUnit": "gr",
      "bulletBc": 0.565,
      "bulletBcModel": "g1",
      "caliber": ".308 Win",
      "caliberId": "308win",
      "caliberMm": 7.62,
      "manufacturerCase": "Lapua"
    },
    {
      "id": "lapua-308win-170gr-sp-mega",
      "name": "Lapua .308 Win 170gr SP Mega",
      "type": "centerfire",
      "manufacturerBullet": "Lapua",
      "bulletName": "Mega SP",
      "bulletWeight": 170,
      "bulletWeightUnit": "gr",
      "bulletBc": 0.41,
      "bulletBcModel": "g1",
      "caliber": ".308 Win",
      "caliberId": "308win",
      "caliberMm": 7.62,
      "manufacturerCase": "Lapua"
    },
    {
      "id": "lapua-308win-185gr-sp-mega",
      "name": "Lapua .308 Win 185gr SP Mega",
      "type": "centerfire",
      "manufacturerBullet": "Lapua",
      "bulletName": "Mega SP",
      "bulletWeight": 185,
      "bulletWeightUnit": "gr",
      "bulletBc": 0.44,
      "bulletBcModel": "g1",
      "caliber": ".308 Win",
      "caliberId": "308win",
      "caliberMm": 7.62,
      "manufacturerCase": "Lapua"
    },
    {
      "id": "lapua-6.5creedmoor-136gr-hpbt-scenar",
      "name": "Lapua 6.5 Creedmoor 136gr HPBT Scenar",
      "type": "centerfire",
      "manufacturerBullet": "Lapua",
      "bulletName": "Scenar HPBT",
      "bulletWeight": 136,
      "bulletWeightUnit": "gr",
      "bulletBc": 0.547,
      "bulletBcModel": "g1",
      "caliber": "6.5 Creedmoor",
      "caliberId": "6.5creedmoor",
      "caliberMm": 6.5,
      "manufacturerCase": "Lapua"
    },
    {
      "id": "lapua-6.5creedmoor-140gr-hpbt-scenar",
      "name": "Lapua 6.5 Creedmoor 140gr HPBT Scenar",
      "type": "centerfire",
      "manufacturerBullet": "Lapua",
      "bulletName": "Scenar HPBT",
      "bulletWeight": 140,
      "bulletWeightUnit": "gr",
      "bulletBc": 0.585,
      "bulletBcModel": "g1",
      "caliber": "6.5 Creedmoor",
      "caliberId": "6.5creedmoor",
      "caliberMm": 6.5,
      "manufacturerCase": "Lapua"
    },
    {
      "id": "lapua-6.5creedmoor-123gr-hpbt-scenar",
      "name": "Lapua 6.5 Creedmoor 123gr HPBT Scenar",
      "type": "centerfire",
      "manufacturerBullet": "Lapua",
      "bulletName": "Scenar HPBT",
      "bulletWeight": 123,
      "bulletWeightUnit": "gr",
      "bulletBc": 0.527,
      "bulletBcModel": "g1",
      "caliber": "6.5 Creedmoor",
      "caliberId": "6.5creedmoor",
      "caliberMm": 6.5,
      "manufacturerCase": "Lapua"
    },
    {
      "id": "lapua-6.5creedmoor-120gr-sp-mega",
      "name": "Lapua 6.5 Creedmoor 120gr SP Mega",
      "type": "centerfire",
      "manufacturerBullet": "Lapua",
      "bulletName": "Mega SP",
      "bulletWeight": 120,
      "bulletWeightUnit": "gr",
      "bulletBc": 0.47,
      "bulletBcModel": "g1",
      "caliber": "6.5 Creedmoor",
      "caliberId": "6.5creedmoor",
      "caliberMm": 6.5,
      "manufacturerCase": "Lapua"
    },
    {
      "id": "lapua-30-06-170gr-sp-mega",
      "name": "Lapua .30-06 Springfield 170gr SP Mega",
      "type": "centerfire",
      "manufacturerBullet": "Lapua",
      "bulletName": "Mega SP",
      "bulletWeight": 170,
      "bulletWeightUnit": "gr",
      "bulletBc": 0.41,
      "bulletBcModel": "g1",
      "caliber": ".30-06 Springfield",
      "caliberId": "30-06",
      "caliberMm": 7.62,
      "manufacturerCase": "Lapua"
    },
    {
      "id": "lapua-30-06-185gr-sp-mega",
      "name": "Lapua .30-06 Springfield 185gr SP Mega",
      "type": "centerfire",
      "manufacturerBullet": "Lapua",
      "bulletName": "Mega SP",
      "bulletWeight": 185,
      "bulletWeightUnit": "gr",
      "bulletBc": 0.44,
      "bulletBcModel": "g1",
      "caliber": ".30-06 Springfield",
      "caliberId": "30-06",
      "caliberMm": 7.62,
      "manufacturerCase": "Lapua"
    },
    {
      "id": "lapua-30-06-155gr-hpbt-scenar",
      "name": "Lapua .30-06 Springfield 155gr HPBT Scenar",
      "type": "centerfire",
      "manufacturerBullet": "Lapua",
      "bulletName": "Scenar HPBT",
      "bulletWeight": 155,
      "bulletWeightUnit": "gr",
      "bulletBc": 0.508,
      "bulletBcModel": "g1",
      "caliber": ".30-06 Springfield",
      "caliberId": "30-06",
      "caliberMm": 7.62,
      "manufacturerCase": "Lapua"
    },
    {
      "id": "lapua-30-06-185gr-hpbt-scenar",
      "name": "Lapua .30-06 Springfield 185gr HPBT Scenar",
      "type": "centerfire",
      "manufacturerBullet": "Lapua",
      "bulletName": "Scenar HPBT",
      "bulletWeight": 185,
      "bulletWeightUnit": "gr",
      "bulletBc": 0.521,
      "bulletBcModel": "g1",
      "caliber": ".30-06 Springfield",
      "caliberId": "30-06",
      "caliberMm": 7.62,
      "manufacturerCase": "Lapua"
    },
    {
      "id": "lapua-300win-185gr-hpbt-scenar",
      "name": "Lapua .300 Win Mag 185gr HPBT Scenar",
      "type": "centerfire",
      "manufacturerBullet": "Lapua",
      "bulletName": "Scenar HPBT",
      "bulletWeight": 185,
      "bulletWeightUnit": "gr",
      "bulletBc": 0.521,
      "bulletBcModel": "g1",
      "caliber": ".300 Win Mag",
      "caliberId": "300win",
      "caliberMm": 7.62,
      "manufacturerCase": "Lapua"
    },
    {
      "id": "lapua-300win-200gr-hpbt-scenar",
      "name": "Lapua .300 Win Mag 200gr HPBT Scenar",
      "type": "centerfire",
      "manufacturerBullet": "Lapua",
      "bulletName": "Scenar HPBT",
      "bulletWeight": 200,
      "bulletWeightUnit": "gr",
      "bulletBc": 0.565,
      "bulletBcModel": "g1",
      "caliber": ".300 Win Mag",
      "caliberId": "300win",
      "caliberMm": 7.62,
      "manufacturerCase": "Lapua"
    },
    {
      "id": "lapua-300win-185gr-sp-mega",
      "name": "Lapua .300 Win Mag 185gr SP Mega",
      "type": "centerfire",
      "manufacturerBullet": "Lapua",
      "bulletName": "Mega SP",
      "bulletWeight": 185,
      "bulletWeightUnit": "gr",
      "bulletBc": 0.44,
      "bulletBcModel": "g1",
      "caliber": ".300 Win Mag",
      "caliberId": "300win",
      "caliberMm": 7.62,
      "manufacturerCase": "Lapua"
    },
    {
      "id": "lapua-270win-150gr-sp-mega",
      "name": "Lapua .270 Win 150gr SP Mega",
      "type": "centerfire",
      "manufacturerBullet": "Lapua",
      "bulletName": "Mega SP",
      "bulletWeight": 150,
      "bulletWeightUnit": "gr",
      "bulletBc": 0.47,
      "bulletBcModel": "g1",
      "caliber": ".270 Win",
      "caliberId": "270win",
      "caliberMm": 7.04,
      "manufacturerCase": "Lapua"
    },
    {
      "id": "lapua-22lr-40gr-center-x",
      "name": "Lapua Center-X .22 LR 40gr",
      "type": "rimfire",
      "manufacturerBullet": "Lapua",
      "bulletName": "Center-X",
      "bulletWeight": 40,
      "bulletWeightUnit": "gr",
      "caliber": ".22 LR",
      "caliberId": "22lr",
      "caliberMm": 5.6,
      "manufacturerCase": "Lapua"
    },
    {
      "id": "lapua-22lr-40gr-midas-m",
      "name": "Lapua Midas+ M .22 LR 40gr",
      "type": "rimfire",
      "manufacturerBullet": "Lapua",
      "bulletName": "Midas+ M",
      "bulletWeight": 40,
      "bulletWeightUnit": "gr",
      "caliber": ".22 LR",
      "caliberId": "22lr",
      "caliberMm": 5.6,
      "manufacturerCase": "Lapua"
    },
    {
      "id": "lapua-22lr-40gr-midas-l",
      "name": "Lapua Midas+ L .22 LR 40gr",
      "type": "rimfire",
      "manufacturerBullet": "Lapua",
      "bulletName": "Midas+ L",
      "bulletWeight": 40,
      "bulletWeightUnit": "gr",
      "caliber": ".22 LR",
      "caliberId": "22lr",
      "caliberMm": 5.6,
      "manufacturerCase": "Lapua"
    },
    {
      "id": "lapua-22lr-40gr-x-act",
      "name": "Lapua X-Act .22 LR 40gr",
      "type": "rimfire",
      "manufacturerBullet": "Lapua",
      "bulletName": "X-Act",
      "bulletWeight": 40,
      "bulletWeightUnit": "gr",
      "caliber": ".22 LR",
      "caliberId": "22lr",
      "caliberMm": 5.6,
      "manufacturerCase": "Lapua"
    },
    {
      "id": "lapua-22lr-40gr-polar-biathlon",
      "name": "Lapua Polar Biathlon .22 LR 40gr",
      "type": "rimfire",
      "manufacturerBullet": "Lapua",
      "bulletName": "Polar Biathlon",
      "bulletWeight": 40,
      "bulletWeightUnit": "gr",
      "caliber": ".22 LR",
      "caliberId": "22lr",
      "caliberMm": 5.6,
      "manufacturerCase": "Lapua"
    },
    {
      "id": "lapua-22lr-40gr-standard-plus",
      "name": "Lapua Standard Plus .22 LR 40gr",
      "type": "rimfire",
      "manufacturerBullet": "Lapua",
      "bulletName": "Standard Plus",
      "bulletWeight": 40,
      "bulletWeightUnit": "gr",
      "caliber": ".22 LR",
      "caliberId": "22lr",
      "caliberMm": 5.6,
      "manufacturerCase": "Lapua"
    },
    {
      "id": "lapua-22lr-40gr-super-club",
      "name": "Lapua Super Club .22 LR 40gr",
      "type": "rimfire",
      "manufacturerBullet": "Lapua",
      "bulletName": "Super Club",
      "bulletWeight": 40,
      "bulletWeightUnit": "gr",
      "caliber": ".22 LR",
      "caliberId": "22lr",
      "caliberMm": 5.6,
      "manufacturerCase": "Lapua"
    },
    {
      "id": "lapua-7mm-rem-mag-155gr-hpbt-scenar",
      "name": "Lapua 7mm Rem Mag 155gr HPBT Scenar",
      "type": "centerfire",
      "manufacturerBullet": "Lapua",
      "bulletName": "Scenar HPBT",
      "bulletWeight": 155,
      "bulletWeightUnit": "gr",
      "bulletBc": 0.547,
      "bulletBcModel": "g1",
      "caliber": "7mm Rem Mag",
      "caliberId": "7mmrem",
      "caliberMm": 7,
      "manufacturerCase": "Lapua"
    },
    {
      "id": "lapua-7mm-rem-mag-180gr-sp-mega",
      "name": "Lapua 7mm Rem Mag 180gr SP Mega",
      "type": "centerfire",
      "manufacturerBullet": "Lapua",
      "bulletName": "Mega SP",
      "bulletWeight": 180,
      "bulletWeightUnit": "gr",
      "bulletBc": 0.52,
      "bulletBcModel": "g1",
      "caliber": "7mm Rem Mag",
      "caliberId": "7mmrem",
      "caliberMm": 7,
      "manufacturerCase": "Lapua"
    },
    {
      "id": "lapua-6.5x55-120gr-sp-mega",
      "name": "Lapua 6.5x55 SE 120gr SP Mega",
      "type": "centerfire",
      "manufacturerBullet": "Lapua",
      "bulletName": "Mega SP",
      "bulletWeight": 120,
      "bulletWeightUnit": "gr",
      "bulletBc": 0.47,
      "bulletBcModel": "g1",
      "caliber": "6.5x55 Swedish",
      "caliberId": "6.5x55",
      "caliberMm": 6.5,
      "manufacturerCase": "Lapua"
    },
    {
      "id": "lapua-6.5x55-123gr-hpbt-scenar",
      "name": "Lapua 6.5x55 SE 123gr HPBT Scenar",
      "type": "centerfire",
      "manufacturerBullet": "Lapua",
      "bulletName": "Scenar HPBT",
      "bulletWeight": 123,
      "bulletWeightUnit": "gr",
      "bulletBc": 0.527,
      "bulletBcModel": "g1",
      "caliber": "6.5x55 Swedish",
      "caliberId": "6.5x55",
      "caliberMm": 6.5,
      "manufacturerCase": "Lapua"
    },
    {
      "id": "lapua-6.5x55-139gr-hpbt-scenar",
      "name": "Lapua 6.5x55 SE 139gr HPBT Scenar",
      "type": "centerfire",
      "manufacturerBullet": "Lapua",
      "bulletName": "Scenar HPBT",
      "bulletWeight": 139,
      "bulletWeightUnit": "gr",
      "bulletBc": 0.615,
      "bulletBcModel": "g1",
      "caliber": "6.5x55 Swedish",
      "caliberId": "6.5x55",
      "caliberMm": 6.5,
      "manufacturerCase": "Lapua"
    },
    {
      "id": "lapua-6.5x55-155gr-sp-mega",
      "name": "Lapua 6.5x55 SE 155gr SP Mega",
      "type": "centerfire",
      "manufacturerBullet": "Lapua",
      "bulletName": "Mega SP",
      "bulletWeight": 155,
      "bulletWeightUnit": "gr",
      "bulletBc": 0.51,
      "bulletBcModel": "g1",
      "caliber": "6.5x55 Swedish",
      "caliberId": "6.5x55",
      "caliberMm": 6.5,
      "manufacturerCase": "Lapua"
    },
    {
      "id": "lapua-243win-90gr-hpbt-scenar",
      "name": "Lapua .243 Win 90gr HPBT Scenar",
      "type": "centerfire",
      "manufacturerBullet": "Lapua",
      "bulletName": "Scenar HPBT",
      "bulletWeight": 90,
      "bulletWeightUnit": "gr",
      "bulletBc": 0.447,
      "bulletBcModel": "g1",
      "caliber": ".243 Win",
      "caliberId": "243win",
      "caliberMm": 6.17,
      "manufacturerCase": "Lapua"
    },
    {
      "id": "lapua-243win-100gr-sp-mega",
      "name": "Lapua .243 Win 100gr SP Mega",
      "type": "centerfire",
      "manufacturerBullet": "Lapua",
      "bulletName": "Mega SP",
      "bulletWeight": 100,
      "bulletWeightUnit": "gr",
      "bulletBc": 0.38,
      "bulletBcModel": "g1",
      "caliber": ".243 Win",
      "caliberId": "243win",
      "caliberMm": 6.17,
      "manufacturerCase": "Lapua"
    },
    {
      "id": "lapua-8x57-200gr-sp-mega",
      "name": "Lapua 8x57 JS 200gr SP Mega",
      "type": "centerfire",
      "manufacturerBullet": "Lapua",
      "bulletName": "Mega SP",
      "bulletWeight": 200,
      "bulletWeightUnit": "gr",
      "bulletBc": 0.44,
      "bulletBcModel": "g1",
      "caliber": "8x57 JS",
      "caliberId": "8x57",
      "caliberMm": 8.2,
      "manufacturerCase": "Lapua"
    },
    {
      "id": "lapua-9.3x62-285gr-sp-mega",
      "name": "Lapua 9.3x62 285gr SP Mega",
      "type": "centerfire",
      "manufacturerBullet": "Lapua",
      "bulletName": "Mega SP",
      "bulletWeight": 285,
      "bulletWeightUnit": "gr",
      "bulletBc": 0.4,
      "bulletBcModel": "g1",
      "caliber": "9.3x62mm",
      "caliberId": "9.3x62",
      "caliberMm": 9.3,
      "manufacturerCase": "Lapua"
    },
    {
      "id": "lapua-22-250-55gr-hpbt-scenar",
      "name": "Lapua .22-250 Rem 55gr HPBT Scenar",
      "type": "centerfire",
      "manufacturerBullet": "Lapua",
      "bulletName": "Scenar HPBT",
      "bulletWeight": 55,
      "bulletWeightUnit": "gr",
      "bulletBc": 0.267,
      "bulletBcModel": "g1",
      "caliber": ".22-250 Rem",
      "caliberId": "22-250",
      "caliberMm": 5.7,
      "manufacturerCase": "Lapua"
    },
    {
      "id": "lapua-260rem-123gr-hpbt-scenar",
      "name": "Lapua .260 Rem 123gr HPBT Scenar",
      "type": "centerfire",
      "manufacturerBullet": "Lapua",
      "bulletName": "Scenar HPBT",
      "bulletWeight": 123,
      "bulletWeightUnit": "gr",
      "bulletBc": 0.527,
      "bulletBcModel": "g1",
      "caliber": ".260 Rem",
      "caliberId": "260rem",
      "caliberMm": 6.5,
      "manufacturerCase": "Lapua"
    },
    {
      "id": "lapua-338lapua-250gr-hpbt-scenar",
      "name": "Lapua .338 Lapua Mag 250gr HPBT Scenar",
      "type": "centerfire",
      "manufacturerBullet": "Lapua",
      "bulletName": "Scenar HPBT",
      "bulletWeight": 250,
      "bulletWeightUnit": "gr",
      "bulletBc": 0.675,
      "bulletBcModel": "g1",
      "caliber": ".338 Lapua Mag",
      "caliberId": "338lapua",
      "caliberMm": 8.6,
      "manufacturerCase": "Lapua"
    },
    {
      "id": "lapua-338lapua-300gr-hpbt-scenar",
      "name": "Lapua .338 Lapua Mag 300gr HPBT Scenar",
      "type": "centerfire",
      "manufacturerBullet": "Lapua",
      "bulletName": "Scenar HPBT",
      "bulletWeight": 300,
      "bulletWeightUnit": "gr",
      "bulletBc": 0.736,
      "bulletBcModel": "g1",
      "caliber": ".338 Lapua Mag",
      "caliberId": "338lapua",
      "caliberMm": 8.6,
      "manufacturerCase": "Lapua"
    },
    {
      "id": "lapua-338lapua-250gr-sp-mega",
      "name": "Lapua .338 Lapua Mag 250gr SP Mega",
      "type": "centerfire",
      "manufacturerBullet": "Lapua",
      "bulletName": "Mega SP",
      "bulletWeight": 250,
      "bulletWeightUnit": "gr",
      "bulletBc": 0.55,
      "bulletBcModel": "g1",
      "caliber": ".338 Lapua Mag",
      "caliberId": "338lapua",
      "caliberMm": 8.6,
      "manufacturerCase": "Lapua"
    },
    {
      "id": "lapua-338lapua-270gr-hpbt-scenar-l",
      "name": "Lapua .338 Lapua Mag 270gr HPBT Scenar-L",
      "type": "centerfire",
      "manufacturerBullet": "Lapua",
      "bulletName": "Scenar-L HPBT",
      "bulletWeight": 270,
      "bulletWeightUnit": "gr",
      "bulletBc": 0.757,
      "bulletBcModel": "g1",
      "caliber": ".338 Lapua Mag",
      "caliberId": "338lapua",
      "caliberMm": 8.6,
      "manufacturerCase": "Lapua"
    },
    {
      "id": "lapua-6mmbr-90gr-hpbt-scenar",
      "name": "Lapua 6mm BR Norma 90gr HPBT Scenar",
      "type": "centerfire",
      "manufacturerBullet": "Lapua",
      "bulletName": "Scenar HPBT",
      "bulletWeight": 90,
      "bulletWeightUnit": "gr",
      "bulletBc": 0.447,
      "bulletBcModel": "g1",
      "caliber": "6mm BR Scenar",
      "caliberId": "6mmbr",
      "caliberMm": 6,
      "manufacturerCase": "Lapua"
    },
    {
      "id": "lapua-6mmbr-105gr-hpbt-scenar",
      "name": "Lapua 6mm BR Norma 105gr HPBT Scenar",
      "type": "centerfire",
      "manufacturerBullet": "Lapua",
      "bulletName": "Scenar HPBT",
      "bulletWeight": 105,
      "bulletWeightUnit": "gr",
      "bulletBc": 0.53,
      "bulletBcModel": "g1",
      "caliber": "6mm BR Scenar",
      "caliberId": "6mmbr",
      "caliberMm": 6,
      "manufacturerCase": "Lapua"
    },
    {
      "id": "lapua-6.5x47lapua-123gr-hpbt-scenar",
      "name": "Lapua 6.5x47 Lapua 123gr HPBT Scenar",
      "type": "centerfire",
      "manufacturerBullet": "Lapua",
      "bulletName": "Scenar HPBT",
      "bulletWeight": 123,
      "bulletWeightUnit": "gr",
      "bulletBc": 0.527,
      "bulletBcModel": "g1",
      "caliber": "6.5x47 Lapua",
      "caliberId": "6.5x47",
      "caliberMm": 6.5,
      "manufacturerCase": "Lapua"
    },
    {
      "id": "lapua-6.5x47lapua-136gr-hpbt-scenar",
      "name": "Lapua 6.5x47 Lapua 136gr HPBT Scenar",
      "type": "centerfire",
      "manufacturerBullet": "Lapua",
      "bulletName": "Scenar HPBT",
      "bulletWeight": 136,
      "bulletWeightUnit": "gr",
      "bulletBc": 0.547,
      "bulletBcModel": "g1",
      "caliber": "6.5x47 Lapua",
      "caliberId": "6.5x47",
      "caliberMm": 6.5,
      "manufacturerCase": "Lapua"
    },
    {
      "id": "lapua-6.5x47lapua-139gr-hpbt-scenar",
      "name": "Lapua 6.5x47 Lapua 139gr HPBT Scenar",
      "type": "centerfire",
      "manufacturerBullet": "Lapua",
      "bulletName": "Scenar HPBT",
      "bulletWeight": 139,
      "bulletWeightUnit": "gr",
      "bulletBc": 0.615,
      "bulletBcModel": "g1",
      "caliber": "6.5x47 Lapua",
      "caliberId": "6.5x47",
      "caliberMm": 6.5,
      "manufacturerCase": "Lapua"
    },
    {
      "id": "lapua-22ppc-55gr-hpbt-scenar",
      "name": "Lapua .22 PPC 55gr HPBT Scenar",
      "type": "centerfire",
      "manufacturerBullet": "Lapua",
      "bulletName": "Scenar HPBT",
      "bulletWeight": 55,
      "bulletWeightUnit": "gr",
      "bulletBc": 0.267,
      "bulletBcModel": "g1",
      "caliber": ".22 PPC",
      "caliberId": "22ppc",
      "caliberMm": 5.7,
      "manufacturerCase": "Lapua"
    },
    {
      "id": "lapua-222rem-55gr-fmj",
      "name": "Lapua .222 Rem 55gr FMJ",
      "type": "centerfire",
      "manufacturerBullet": "Lapua",
      "bulletName": "FMJ",
      "bulletWeight": 55,
      "bulletWeightUnit": "gr",
      "bulletBc": 0.267,
      "bulletBcModel": "g1",
      "caliber": ".222 Rem",
      "caliberId": "222rem",
      "caliberMm": 5.7,
      "manufacturerCase": "Lapua"
    },
    {
      "id": "lapua-9mm-123gr-fmj",
      "name": "Lapua 9mm Luger 123gr FMJ",
      "type": "centerfire",
      "manufacturerBullet": "Lapua",
      "bulletName": "FMJ",
      "bulletWeight": 123,
      "bulletWeightUnit": "gr",
      "caliber": "9mm Luger",
      "caliberId": "9mm",
      "caliberMm": 9,
      "manufacturerCase": "Lapua"
    },
    {
      "id": "lapua-32swl-98gr-wadcutter",
      "name": "Lapua .32 S&W Long 98gr Wadcutter",
      "type": "centerfire",
      "manufacturerBullet": "Lapua",
      "bulletName": "Wadcutter",
      "bulletWeight": 98,
      "bulletWeightUnit": "gr",
      "caliber": ".32 S&W Long",
      "caliberId": "32swl",
      "caliberMm": 7.94,
      "manufacturerCase": "Lapua"
    }
  ]